mogestpy/__init__.py
mogestpy/quality/__init__.py
mogestpy/quality/buwo.py
mogestpy/quality/zero_d.py
mogestpy/quantity/__init__.py
mogestpy/quantity/Hydrodynamic/SaintVenant.py
mogestpy/quantity/Hydrodynamic/SIHQUAL.py
mogestpy/quantity/Hydrodynamic/SIHQUALInputs/boundary_c.csv
mogestpy/quantity/Hydrodynamic/SIHQUALInputs/boundary_Q.csv
mogestpy/quantity/Hydrodynamic/SIHQUALInputs/boundary_y.csv
mogestpy/quantity/Hydrodynamic/SIHQUALInputs/lateral_c.csv
mogestpy/quantity/Hydrodynamic/SIHQUALInputs/lateral_Q.csv
mogestpy/quantity/Hydrological/MassBalance.py
mogestpy/quantity/Hydrological/Muskingum.py
mogestpy/quantity/Hydrological/SMAP.py
mogestpy/quantity/Hydrological/SMAP2.py
mogestpy-0.1.0.dist-info/LICENSE.md
mogestpy-0.1.0.dist-info/METADATA
mogestpy-0.1.0.dist-info/WHEEL
mogestpy-0.1.0.dist-info/RECORD
