Metadata-Version: 2.3
Name: mogestpy
Version: 0.1.0
Summary: Water resources management model based on hydrological and hydronimic models
License: MIT
Keywords: hydrology,water resouces,hydrological model
Author: Dario Hachisu Hossoda
Author-email: dario.hossoda@usp.br
Requires-Python: >=3.9,<4.0
Classifier: License :: OSI Approved :: MIT License
Classifier: Programming Language :: Python :: 3
Classifier: Programming Language :: Python :: 3.9
Classifier: Programming Language :: Python :: 3.10
Classifier: Programming Language :: Python :: 3.11
Classifier: Programming Language :: Python :: 3.12
Classifier: Programming Language :: Python :: 3.13
Requires-Dist: pandas (>=2.2.3,<3.0.0)
Requires-Dist: scikit-learn (>=1.5.2,<2.0.0)
Requires-Dist: spotpy (>=1.6.2,<2.0.0)
Project-URL: Bug Tracker, https://github.com/dariohhossoda/MOGESTpy/issues
Project-URL: Homepage, https://github.com/dariohhossoda/MOGESTpy
Project-URL: Repository, https://github.com/dariohhossoda/MOGESTpy
